herm/__init__.py
herm/client.py
herm/tests/__init__.py
herm/tests/test_basic.py
herm-0.1.dist-info/LICENSE
herm-0.1.dist-info/METADATA
herm-0.1.dist-info/WHEEL
herm-0.1.dist-info/top_level.txt
herm-0.1.dist-info/zip-safe
herm-0.1.dist-info/RECORD
